[
	{
		"url": "https://www.baidu.com/",
		"headers": {
			"Accept": "text/html, application/xhtml+xml, application/xml; q=0.9, */*; q=0.8",
			"Accept-Language": "zh-CN,zh;q=0.9",
			"Connection": "Keep-Alive",
			"Host": "www.baidu.com",
			"Referer": "Cache-Control",
			"Cache-Control": "max-age=0",
			"Upgrade-Insecure-Requests": "1",
			"User-Agent": "Mozilla/5.0 (Windows NT 10.0; Win64; x64) AppleWebKit/537.36 (KHTML, like Gecko) Chrome/64.0.3282.140 Safari/537.36 Edge/17.17134"
		}
	},
	{
		"url": "https://pan.baidu.com/",
		"headers": {
			"Accept": "text/html,application/xhtml+xml,application/xml;q=0.9,image/webp,image/apng,*/*;q=0.8",
			"Accept-Language": "zh-CN,zh;q=0.9",
			"Cache-Control": "max-age=0",
			"Connection": "keep-alive",
			"Host": "pan.baidu.com",
			"Referer": "https://www.hao123.com/",
			"Upgrade-Insecure-Requests": "1",
			"User-Agent": "Mozilla/5.0 (Windows NT 10.0; WOW64) AppleWebKit/537.36 (KHTML, like Gecko) Chrome/69.0.3486.0 Safari/537.36"
		}
	},
	{
		"url": "https://passport.baidu.com",
		"headers": {
			"Accept": "text/html,application/xhtml+xml,application/xml;q=0.9,image/webp,image/apng,*/*;q=0.8",
			"Accept-Language": "zh-CN,zh;q=0.9",
			"Cache-Control": "max-age=0",
			"Connection": "keep-alive",
			"Host": "passport.baidu.com",
			"Referer": "https://pan.baidu.com/",
			"Upgrade-Insecure-Requests": "1",
			"User-Agent": "Mozilla/5.0 (Windows NT 10.0; WOW64) AppleWebKit/537.36 (KHTML, like Gecko) Chrome/69.0.3486.0 Safari/537.36"
		}
	},
	{
		"url": "http://tieba.baidu.com/",
		"headers": {
			"Accept": "text/html,application/xhtml+xml,application/xml;q=0.9,image/webp,image/apng,*/*;q=0.8",
			"Accept-Language": "zh-CN,zh;q=0.9",
			"Cache-Control": "max-age=0",
			"Connection": "keep-alive",
			"Host": "tieba.baidu.com",
			"Referer": "https://www.baidu.com/",
			"Upgrade-Insecure-Requests": "1",
			"User-Agent": "Mozilla/5.0 (Windows NT 10.0; WOW64) AppleWebKit/537.36 (KHTML, like Gecko) Chrome/69.0.3486.0 Safari/537.36"
		}
	}
]